aws_mail/__init__.py
aws_mail/_version.py
aws_mail/aws_mail.py
aws_mail-0.0.7.data/scripts/aws_mail
aws_mail-0.0.7.dist-info/METADATA
aws_mail-0.0.7.dist-info/WHEEL
aws_mail-0.0.7.dist-info/top_level.txt
aws_mail-0.0.7.dist-info/RECORD
