Metadata-Version: 2.1
Name: aws-mail
Version: 0.0.7
Summary: AWS sendmail replacement using boto3.
Home-page: https://github.com/normoes/aws_mail
Author: Norman Moeschter-Schenck
Author-email: norman.moeschter@gmail.com
Maintainer: Norman Moeschter-Schenck
Maintainer-email: <norman.moeschter@gmail.com>
License: UNKNOWN
Download-URL: https://github.com/normoes/aws_mail/archive/v0.0.7.tar.gz
Platform: UNKNOWN
Classifier: Development Status :: 5 - Production/Stable
Classifier: Intended Audience :: Developers
Classifier: License :: OSI Approved :: MIT License
Classifier: Natural Language :: English
Classifier: Programming Language :: Python
Requires-Dist: eventhooks[aws] (>=0.3)
Requires-Dist: pyyaml (>=5.4.1)
